MANIFEST.in
README.md
requirements.txt
setup.cfg
setup.py
slide2pdf/__init__.py
slide2pdf/command.py
slide2pdf/slide2pdf.py
slide2pdf.egg-info/PKG-INFO
slide2pdf.egg-info/SOURCES.txt
slide2pdf.egg-info/dependency_links.txt
slide2pdf.egg-info/entry_points.txt
slide2pdf.egg-info/not-zip-safe
slide2pdf.egg-info/requires.txt
slide2pdf.egg-info/top_level.txt