Metadata-Version: 1.0
Name: slide2pdf
Version: 0.2
Summary: slide2pdf is a command line tool to convert html slide presenation to pdf
Home-page: https://github.com/vengatlnx/slide2pdf
Author: Vengatesh.S
Author-email: vengat.lnx@gmail.com
License: MIT
Platform: UNKNOWN
